ghlog/__init__.py
ghlog/cli.py
ghlog/config_access.py
ghlog-1.1.5.dist-info/LICENSE
ghlog-1.1.5.dist-info/METADATA
ghlog-1.1.5.dist-info/WHEEL
ghlog-1.1.5.dist-info/entry_points.txt
ghlog-1.1.5.dist-info/top_level.txt
ghlog-1.1.5.dist-info/RECORD
