Metadata-Version: 2.1
Name: ghlog
Version: 1.1.5
Summary: A simple logbook that upload to github
Home-page: https://github.com/lukew3/ghlog
Author: Luke Weiler
Author-email: lukew25073@gmail.com
License: MIT
Platform: UNKNOWN
Requires-Dist: pygithub
Requires-Dist: tqdm
Requires-Dist: click
